LICENSE
MANIFEST.in
README.md
pyproject.toml
setup.py
nyxstone/__init__.py
nyxstone-cpp/pynyxstone.cpp
nyxstone-cpp/include/nyxstone.h
nyxstone-cpp/src/ELFStreamerWrapper.cpp
nyxstone-cpp/src/ELFStreamerWrapper.h
nyxstone-cpp/src/ObjectWriterWrapper.cpp
nyxstone-cpp/src/ObjectWriterWrapper.h
nyxstone-cpp/src/nyxstone.cpp
nyxstone-cpp/src/Target/AArch64/MCTargetDesc/AArch64FixupKinds.h
nyxstone-cpp/src/Target/AArch64/MCTargetDesc/AArch64MCExpr.h
nyxstone-cpp/src/Target/ARM/MCTargetDesc/ARMFixupKinds.h
nyxstone-cpp/vendor/.clang-tidy
nyxstone-cpp/vendor/argh.h
nyxstone-cpp/vendor/expected.hpp
nyxstone.egg-info/PKG-INFO
nyxstone.egg-info/SOURCES.txt
nyxstone.egg-info/dependency_links.txt
nyxstone.egg-info/top_level.txt
tests/test.py