Metadata-Version: 2.1
Name: nyxstone
Version: 0.1.1
Summary: Python bindings for the nyxstone library.
Author: emproof B.V.
Author-email: oss@emproof.com
License-File: LICENSE
